distinfo_readme/__init__.py
distinfo_readme/__main__.py
distinfo_readme/main.py
distinfo_readme/resources/css.css
distinfo_readme/resources/favicon.ico
distinfo_readme/resources/readme-ltr.css
DistInfo_ReadMe-1.0.0.dist-info/LICENSE
DistInfo_ReadMe-1.0.0.dist-info/METADATA
DistInfo_ReadMe-1.0.0.dist-info/WHEEL
DistInfo_ReadMe-1.0.0.dist-info/entry_points.txt
DistInfo_ReadMe-1.0.0.dist-info/top_level.txt
DistInfo_ReadMe-1.0.0.dist-info/RECORD
