Metadata-Version: 2.1
Name: DistInfo-ReadMe
Version: 1.0.0
Summary: A postviewing of the readme of installed Python projects
Author: Stephan Zevenhuizen
Author-email: S.J.M.Zevenhuizen@uu.nl
License: BSD-2-Clause
Keywords: .dist-info,readme,metadata,viewing,site-packages,postview,preview,project,description,test
Classifier: Topic :: Documentation
Classifier: Topic :: Software Development :: Documentation
Classifier: Topic :: Software Development :: Libraries :: Python Modules
Classifier: Topic :: Text Processing :: Markup
Classifier: Development Status :: 5 - Production/Stable
Classifier: License :: OSI Approved :: BSD License
Classifier: Programming Language :: Python :: 3
Classifier: Operating System :: OS Independent
Classifier: Environment :: Console
Classifier: Environment :: Web Environment
Classifier: Intended Audience :: Developers
Classifier: Natural Language :: English
Requires-Python: >=3.8
License-File: LICENSE
Requires-Dist: readme-renderer[md]
